setup.py
metaq/__init__.py
metaq/producer.py
metaq/zkclient.py
metaq.egg-info/PKG-INFO
metaq.egg-info/SOURCES.txt
metaq.egg-info/dependency_links.txt
metaq.egg-info/requires.txt
metaq.egg-info/top_level.txt